mailcli/__about__.py
mailcli/__init__.py
mailcli/mailcli.py
mailcli-0.3.1.dist-info/METADATA
mailcli-0.3.1.dist-info/RECORD
mailcli-0.3.1.dist-info/WHEEL
mailcli-0.3.1.dist-info/entry_points.txt
mailcli-0.3.1.dist-info/top_level.txt
