Metadata-Version: 2.1
Name: mailcli
Version: 0.3.1
Summary: Mail-CLI, send mail with mailgun service.
Home-page: https://github.com/debugtalk/mail-cli.git
Author: debugtalk
Author-email: mail@debugtalk.com
License: MIT
Keywords: mail cli jenkins
Platform: UNKNOWN
Classifier: Development Status :: 3 - Alpha
Classifier: Programming Language :: Python :: 2.7
Classifier: Programming Language :: Python :: 3.4
Classifier: Programming Language :: Python :: 3.5
Classifier: Programming Language :: Python :: 3.6
Classifier: Programming Language :: Python :: 3.7
Requires-Python: >=2.7, !=3.0.*, !=3.1.*, !=3.2.*, !=3.3.*, <4
